LICENCE
README.md
setup.py
bin/pypros_run
pypros/__init__.py
pypros/pros.py
pypros/psychrometrics.py
pypros/ros_methods.py
pypros.egg-info/PKG-INFO
pypros.egg-info/SOURCES.txt
pypros.egg-info/dependency_links.txt
pypros.egg-info/requires.txt
pypros.egg-info/top_level.txt