Metadata-Version: 2.1
Name: pypros
Version: 0.0.12
Summary: pyPROS: Precipitation type calculation, rain or snow
Home-page: https://github.com/pypa/sampleproject
License: UNKNOWN
Platform: UNKNOWN
Classifier: Development Status :: 2 - Pre-Alpha
Classifier: Intended Audience :: Science/Research
Classifier: Topic :: Scientific/Engineering
Classifier: Topic :: Scientific/Engineering :: Atmospheric Science
Classifier: License :: OSI Approved :: BSD License
Classifier: Programming Language :: Python :: 3
Classifier: Programming Language :: Python :: 3.9
License-File: LICENCE
